rnl_edge_sdk/__init__.py
rnl_edge_sdk/auth.py
rnl_edge_sdk/compass.py
rnl_edge_sdk/documents.py
rnl_edge_sdk/environment.py
rnl_edge_sdk/feedback.py
rnl_edge_sdk/others.py
rnl_edge_sdk/prompt.py
rnl_edge_sdk/rag.py
rnl_edge_sdk/rnl_edge_client.py
rnl_edge_sdk/entities/__init__.py
rnl_edge_sdk/entities/data_source.py
rnl_edge_sdk/entities/endpoint.py
rnl_edge_sdk/entities/organization.py
rnl_edge_sdk/entities/product.py
rnl_edge_sdk/exceptions/__init__.py
rnl_edge_sdk/exceptions/rnl_edge_client_exception.py
rnl_edge_sdk/requests/__init__.py
rnl_edge_sdk/requests/delete_multiple_documents_request.py
rnl_edge_sdk/requests/get_organizations_request.py
rnl_edge_sdk/requests/post_document_request.py
rnl_edge_sdk/responses/__init__.py
rnl_edge_sdk/responses/get_documents_response.py
rnl_edge_sdk/responses/get_member_orgs_response.py
rnl_edge_sdk/responses/get_organizations_response.py
rnl_edge_sdk/responses/post_document_response.py
rnl_edge_sdk-1.0.1.dist-info/LICENSE
rnl_edge_sdk-1.0.1.dist-info/METADATA
rnl_edge_sdk-1.0.1.dist-info/WHEEL
rnl_edge_sdk-1.0.1.dist-info/top_level.txt
rnl_edge_sdk-1.0.1.dist-info/RECORD
