Metadata-Version: 2.1
Name: rnl-edge-sdk
Version: 1.0.1
Summary: Python SDK for RNL Edge API
Home-page: https://github.com/ruffalo-noel-levitz/ai-rnl-edge-api/tree/master/rnl-edge-sdk/rnl-edge-sdk-python
Author: Baby Manisha Sunkara
Author-email: babymaneesha@gmail.com
Classifier: Programming Language :: Python :: 3
Classifier: License :: OSI Approved :: MIT License
Classifier: Operating System :: OS Independent
Requires-Python: >=3.6
License-File: LICENSE
Requires-Dist: requests>=2.26.0
